MANIFEST.in
requirements.txt
setup.py
LT2OpenCorpora.egg-info/PKG-INFO
LT2OpenCorpora.egg-info/SOURCES.txt
LT2OpenCorpora.egg-info/dependency_links.txt
LT2OpenCorpora.egg-info/not-zip-safe
LT2OpenCorpora.egg-info/requires.txt
LT2OpenCorpora.egg-info/top_level.txt
bin/lt_convert.py
bin/lt_plot.py
lt2opencorpora/__init__.py
lt2opencorpora/convert.py
lt2opencorpora/mapping.csv
lt2opencorpora/open_corpora_tagset.xml