Metadata-Version: 1.1
Name: LT2OpenCorpora
Version: 1.0.1
Summary: Python script to convert Ukrainian morphological dictionary from LanguageTool project to OpenCorpora forma
Home-page: https://github.com/dchaplinsky/LT2OpenCorpora
Author: Dmitry Chaplinsky
Author-email: chaplinsky.dmitry@gmail.com
License: MIT license
Platform: UNKNOWN
Classifier: Intended Audience :: Developers
Classifier: Intended Audience :: Science/Research
Classifier: License :: OSI Approved :: MIT License
Classifier: Programming Language :: Python
Classifier: Programming Language :: Python :: 2
Classifier: Programming Language :: Python :: 2.7
Classifier: Programming Language :: Python :: Implementation :: CPython
Classifier: Programming Language :: Python :: Implementation :: PyPy
Classifier: Topic :: Software Development :: Libraries :: Python Modules
Classifier: Topic :: Scientific/Engineering :: Information Analysis
Classifier: Topic :: Text Processing :: Linguistic
